fps_yjs/__init__.py
fps_yjs/main.py
fps_yjs/py.typed
fps_yjs/routes.py
fps_yjs/ywebsocket/__init__.py
fps_yjs/ywebsocket/asgi_server.py
fps_yjs/ywebsocket/awareness.py
fps_yjs/ywebsocket/django_channels_consumer.py
fps_yjs/ywebsocket/websocket.py
fps_yjs/ywebsocket/websocket_provider.py
fps_yjs/ywebsocket/websocket_server.py
fps_yjs/ywebsocket/yroom.py
fps_yjs/ywebsocket/ystore.py
fps_yjs/ywebsocket/yutils.py
fps_yjs/ywidgets/__init__.py
fps_yjs/ywidgets/widgets.py
fps_yjs-0.11.4.dist-info/licenses/COPYING.md
fps_yjs-0.11.4.dist-info/WHEEL
fps_yjs-0.11.4.dist-info/entry_points.txt
fps_yjs-0.11.4.dist-info/METADATA
fps_yjs-0.11.4.dist-info/RECORD
