Metadata-Version: 2.4
Name: fps_yjs
Version: 0.11.4
Summary: An FPS plugin for the Yjs API
Keywords: jupyter,server,fastapi,plugins
Author: Jupyter Development Team
Author-email: Jupyter Development Team <jupyter@googlegroups.com>
License-Expression: BSD-3-Clause
License-File: COPYING.md
Classifier: Development Status :: 5 - Production/Stable
Classifier: Intended Audience :: Developers
Classifier: License :: OSI Approved :: BSD License
Classifier: Programming Language :: Python
Classifier: Programming Language :: Python :: 3.10
Classifier: Programming Language :: Python :: 3.11
Classifier: Programming Language :: Python :: 3.12
Classifier: Programming Language :: Python :: 3.13
Classifier: Programming Language :: Python :: 3.14
Classifier: Programming Language :: Python :: Implementation :: CPython
Classifier: Programming Language :: Python :: Implementation :: PyPy
Requires-Dist: pycrdt>=0.9.0,<0.13.0
Requires-Dist: jupyverse-api>=0.12.0,<0.13.0
Requires-Dist: sqlite-anyio>=0.2.0,<0.3.0
Requires-Dist: jupyter-ydoc>3.0.1,<4.0.0
Requires-Dist: anyioutils>=0.7.4
Requires-Python: >=3.10
Project-URL: Homepage, https://jupyter.org
